philomena/__init__.py
philomena/parser.py
philomena/philomena.py
philomena-0.1.0.dist-info/METADATA
philomena-0.1.0.dist-info/WHEEL
philomena-0.1.0.dist-info/top_level.txt
philomena-0.1.0.dist-info/RECORD
